dora_mujoco_husky/__init__.py
dora_mujoco_husky/__main__.py
dora_mujoco_husky/main.py
dora_mujoco_husky/mesh_downloader.py
dora_mujoco_husky-0.2.0.dist-info/METADATA
dora_mujoco_husky-0.2.0.dist-info/WHEEL
dora_mujoco_husky-0.2.0.dist-info/entry_points.txt
dora_mujoco_husky-0.2.0.dist-info/top_level.txt
dora_mujoco_husky-0.2.0.dist-info/RECORD
