Metadata-Version: 2.4
Name: dora-mujoco-husky
Version: 0.2.0
Summary: dora-mujoco-husky
Author-email: Shashwat Patil <email@email.com>
License: MIT
Requires-Python: >=3.10
Requires-Dist: dora-rs>=0.3.9
Requires-Dist: mujoco>=3.1.6
Requires-Dist: pyarrow>=14.0.1
Requires-Dist: huggingface_hub>=0.20.3
